nokey/__init__.py
nokey/activities/bored_api.py
nokey/animals/__init__.py
nokey/animals/dog_api.py
nokey/art_and_images/__init__.py
nokey/art_and_images/artic.py
nokey/art_and_images/lorem_picsum.py
nokey/books_and_literature/__init__.py
nokey/books_and_literature/gutendex.py
nokey/books_and_literature/stephen_king.py
nokey/calendar/__init__.py
nokey/calendar/nager_date.py
nokey/country_info/__init__.py
nokey/country_info/rest_country.py
nokey/developer_tools/__init__.py
nokey/developer_tools/apis_guru.py
nokey/developer_tools/filter_lists.py
nokey/developer_tools/microlink.py
nokey/developer_tools/url_haus.py
nokey/developer_tools/url_shortener.py
nokey/education/__init__.py
nokey/education/university_domains_and_names.py
nokey/finance_and_crypto/__init__.py
nokey/finance_and_crypto/coinmap.py
nokey/finance_and_crypto/exchange_api.py
nokey/finance_and_crypto/wallstreet_bets.py
nokey/food/__init__.py
nokey/food/fruityvice.py
nokey/games/__init__.py
nokey/games/free_to_game.py
nokey/games/open_trivia_db.py
nokey/games/shadify.py
nokey/geolocation/__init__.py
nokey/geolocation/ip_api.py
nokey/geolocation/zippopotamus.py
nokey/government/__init__.py
nokey/government/federal_register.py
nokey/government/usa_spending.py
nokey/health/__init__.py
nokey/health/open_disease.py
nokey/helperFuncs/__init__.py
nokey/helperFuncs/get_api_list.py
nokey/helperFuncs/make_request.py
nokey/helperFuncs/nokey_apis.py
nokey/helperFuncs/throttler.py
nokey/inspiration/__init__.py
nokey/inspiration/dictum.py
nokey/jokes/__init__.py
nokey/jokes/joke_api.py
nokey/language/__init__.py
nokey/language/free_dictionary.py
nokey/random/__init__.py
nokey/random/random_user.py
nokey/science_and_nature/__init__.py
nokey/science_and_nature/integrated_taxonomic_information_system.py
nokey/science_and_nature/nobel_prize.py
nokey/spaceflight/__init__.py
nokey/spaceflight/spaceflight_news.py
nokey/tv_and_film/__init__.py
nokey/tv_and_film/star_trek_api.py
nokey/weather/__init__.py
nokey-0.7.4.dist-info/LICENSE
nokey-0.7.4.dist-info/METADATA
nokey-0.7.4.dist-info/WHEEL
nokey-0.7.4.dist-info/RECORD
