Metadata-Version: 2.1
Name: nokey
Version: 0.7.4
Summary: A python package for accessing APIs that require no key.
Home-page: https://github.com/SpyderRex/nokey
License: MIT
Keywords: API,requests,xmltodict
Author: Spyder Rex
Author-email: billyjohnsonauthor@gmail.com
Requires-Python: >=3.8,<4.0
Classifier: License :: OSI Approved :: MIT License
Classifier: Operating System :: OS Independent
Classifier: Programming Language :: Python :: 3
Classifier: Programming Language :: Python :: 3.8
Classifier: Programming Language :: Python :: 3.9
Classifier: Programming Language :: Python :: 3.10
Classifier: Programming Language :: Python :: 3.11
Classifier: Programming Language :: Python :: 3.12
Requires-Dist: requests (>=2.26.0,<3.0.0)
Requires-Dist: requests-cache (==1.2.0)
Requires-Dist: xmltodict (==0.13.0)
Project-URL: Repository, https://github.com/SpyderRex/nokey
